zeblok/__init__.py
zeblok/api.py
zeblok/auth.py
zeblok/datalake.py
zeblok/dataset.py
zeblok/llm.py
zeblok/microservice.py
zeblok/namespace.py
zeblok/orchestration.py
zeblok/pipeline.py
zeblok/plan.py
zeblok/base/__init__.py
zeblok/base/base_airuns.py
zeblok/base/base_auth.py
zeblok/base/base_datalake.py
zeblok/base/base_service.py
zeblok/base/base_zbl.py
zeblok/utils/__init__.py
zeblok/utils/error_message.py
zeblok/utils/errors.py
zeblok/utils/misc.py
zeblok/utils/progressbar.py
zeblok/utils/validations.py
zeblok_sdk-1.4.0.dist-info/LICENSE.md
zeblok_sdk-1.4.0.dist-info/METADATA
zeblok_sdk-1.4.0.dist-info/WHEEL
zeblok_sdk-1.4.0.dist-info/top_level.txt
zeblok_sdk-1.4.0.dist-info/RECORD
