Metadata-Version: 2.1
Name: zeblok-sdk
Version: 1.4.0
Summary: Zeblok Python SDK
Home-page: 
Author: Karan Pathak
Author-email: karan@dataturtles.com
Maintainer: Zeblok, Karan Pathak
Maintainer-email: zeblok@zeblok.com, karan.pathak@zeblok.com
Keywords: zeblok,python-sdk,zeblok-sdk
Classifier: Programming Language :: Python :: 3
Requires-Python: >=3.9
License-File: LICENSE.md
Requires-Dist: boto3
Requires-Dist: requests
Requires-Dist: minio
Requires-Dist: azure-storage-blob
